octodns_sakuracloud/__init__.py
octodns_sakuracloud-0.0.1.dist-info/LICENSE
octodns_sakuracloud-0.0.1.dist-info/METADATA
octodns_sakuracloud-0.0.1.dist-info/WHEEL
octodns_sakuracloud-0.0.1.dist-info/top_level.txt
octodns_sakuracloud-0.0.1.dist-info/RECORD
